game.py
gameSooyey-0.0.6.dist-info/METADATA
gameSooyey-0.0.6.dist-info/WHEEL
gameSooyey-0.0.6.dist-info/top_level.txt
gameSooyey-0.0.6.dist-info/RECORD
