Metadata-Version: 2.1
Name: gameSooyey
Version: 0.0.6
Summary: Making games easier!
Home-page: UNKNOWN
Author: sooyey
Author-email: sooyooshung@gmail.com
License: MIT
Platform: UNKNOWN
Requires-Python: >=3
